chem_eclipse/ECLIPSEInference.py
chem_eclipse/ECLIPSERuntimeAnalysis.py
chem_eclipse/ECLIPSETrain.py
chem_eclipse/ModelAnalysis.py
chem_eclipse/ProductPredictionTrain.py
chem_eclipse/__init__.py
chem_eclipse/hiclass/BinaryPolicy.py
chem_eclipse/hiclass/ConstantClassifier.py
chem_eclipse/hiclass/Explainer.py
chem_eclipse/hiclass/FlatClassifier.py
chem_eclipse/hiclass/HierarchicalClassifier.py
chem_eclipse/hiclass/LICENSE
chem_eclipse/hiclass/LocalClassifierPerLevel.py
chem_eclipse/hiclass/LocalClassifierPerNode.py
chem_eclipse/hiclass/LocalClassifierPerParentNode.py
chem_eclipse/hiclass/MultiLabelHierarchicalClassifier.py
chem_eclipse/hiclass/MultiLabelLocalClassifierPerNode.py
chem_eclipse/hiclass/MultiLabelLocalClassifierPerParentNode.py
chem_eclipse/hiclass/Pipeline.py
chem_eclipse/hiclass/__init__.py
chem_eclipse/hiclass/_calibration/BetaCalibrator.py
chem_eclipse/hiclass/_calibration/BinaryCalibrator.py
chem_eclipse/hiclass/_calibration/Calibrator.py
chem_eclipse/hiclass/_calibration/IsotonicRegression.py
chem_eclipse/hiclass/_calibration/PlattScaling.py
chem_eclipse/hiclass/_calibration/VennAbersCalibrator.py
chem_eclipse/hiclass/_calibration/__init__.py
chem_eclipse/hiclass/_calibration/calibration_utils.py
chem_eclipse/hiclass/_hiclass_utils.py
chem_eclipse/hiclass/_version.py
chem_eclipse/hiclass/datasets.py
chem_eclipse/hiclass/metrics.py
chem_eclipse/hiclass/probability_combiner/ArithmeticMeanCombiner.py
chem_eclipse/hiclass/probability_combiner/GeometricMeanCombiner.py
chem_eclipse/hiclass/probability_combiner/MultiplyCombiner.py
chem_eclipse/hiclass/probability_combiner/ProbabilityCombiner.py
chem_eclipse/hiclass/probability_combiner/__init__.py
chem_eclipse/models/BaseModel.py
chem_eclipse/models/ECLIPSEModel.py
chem_eclipse/models/ECLIPSEModel_config.json
chem_eclipse/models/ECLIPSEProdModel.py
chem_eclipse/models/ECLIPSEProdModel_config.json
chem_eclipse/models/TransformerModel.py
chem_eclipse/models/TransformerModel_config.json
chem_eclipse-0.1.0.dist-info/licenses/LICENSE.md
chem_eclipse-0.1.0.dist-info/WHEEL
chem_eclipse-0.1.0.dist-info/entry_points.txt
chem_eclipse-0.1.0.dist-info/METADATA
chem_eclipse-0.1.0.dist-info/RECORD
