Metadata-Version: 2.4
Name: chem-eclipse
Version: 0.1.0
Summary: Code for the Paper 'Predicting Enzyme-Compound Interactions for Enzyme-Catalysed Reactions'
Author: Liam Brydon-Brown
Author-email: Liam Brydon-Brown <lbry121@aucklanduni.ac.nz>
License-Expression: GPL-3.0-only
License-File: LICENSE.md
Classifier: Programming Language :: Python :: 3
Classifier: Operating System :: OS Independent
Requires-Dist: scikit-learn<1.5.0
Requires-Dist: xgboost~=3.0.5
Requires-Dist: rdkit~=2024.9.6
Requires-Dist: tqdm
Requires-Dist: matplotlib~=3.10.7
Requires-Dist: pandas~=2.3.3
Requires-Dist: iterative-stratification~=0.1.9
Requires-Dist: envipath-python
Requires-Dist: lightning~=2.5.5
Requires-Dist: tensorboard~=2.18.0
Requires-Dist: plotly
Requires-Dist: cairosvg~=2.8.2
Requires-Dist: kaleido~=1.1.0
Requires-Dist: torch~=2.8.0 ; extra == 'cpu'
Requires-Dist: torch~=2.8.0 ; extra == 'cuda'
Requires-Dist: cupy-cuda12x~=13.5.1 ; extra == 'cuda'
Requires-Python: >=3.12
Project-URL: Homepage, https://github.com/MyCreativityOutlet/chem-eclipse
Project-URL: Issues, https://github.com/MyCreativityOutlet/chem-eclipse/issues
Provides-Extra: cpu
Provides-Extra: cuda
